{"1442741460608":{"imageLocation":"/scans/1442741460608.jpg","id":1442741460608,"full_text":"﻿             SPORT CHEK                           \r\n       550 King Street North                      \r\n         Waterloo, N2L 5W6                        \r\n           (519) 886-6336                         \r\nDate: 9/08/15                                     \r\n                                                  \r\nCashier:20103 JANELLE..F                          \r\n                                                  \r\n                                                  \r\nRegular Sole                                      \r\nU.P.C    Description    Ext $ Qty                 \r\n                                                  \r\nSales Assoc j| 15413 ERIC_D                       \r\n886061273078 DUAL FUSION TR $99.99 1H             \r\n                                                  \r\nSub Total                          $99.99         \r\nTotal Tax                          $13.00         \r\nTotal                             $112.99         \r\nVisa                              $112.99         \r\n##*####*####2966                                  \r\nONFedHST           5.00%            $5.00         \r\nONProvHST          8.00%            $8.00         \r\n                                                  \r\n ###################*#######*#####*#####*         \r\n        TELL US HOW UE DID TODAY!                 \r\n                                                  \r\n Take a short Survey & enter our monthly          \r\n  draw for 1 of 2 $500 Gift Cards! Go to          \r\n      www.SportChekSurvey,ca or call              \r\n             1“866-364-0818.                      \r\n","business_name":"SPORT CHEK","phone_number":"(519) 886-6336","address":"550 King Street North Waterloo, N2L 5W6","total_price":"112.99","line_items":[{"name":"886061273078 DUAL FUSION TR","price":"$99.99"}],"businessName":"SPORT CHEK","phoneNumber":"(519) 886-6336","totalPrice":"112.99"},"1442742564376":{"imageLocation":"/scans/1442742564376.jpg","id":1442742564376,"full_text":"﻿                               SPORT CHEK              \r\n                   550 Kin9 Street North               \r\n                    Waterloo, N2L 51*16                \r\n                      (519) 886-6336                   \r\n                                                       \r\nDate: 9/08/15                                          \r\nCashier:20103 JANELLE..F                               \r\n                                                       \r\n                                                       \r\nRegular Sale                                           \r\nU.P.C    Description    Ext $ Qty                      \r\n                                                       \r\nSales Assoc #: 15^13 ERIC.D                            \r\n886061273078 DUAL FUSION TR $99.99 1H                  \r\n                                                       \r\n                                                       \r\nSub Total                                  $99.99      \r\nTotal Tax                                  $13.00      \r\nTotal                                     $112.99      \r\nVisa                                      $112.99      \r\n#*##*#######2966                                       \r\nONFedHST    5.00%                           $5.00      \r\nONProvHST    8.00%                          $8.00      \r\n                                                       \r\n ###*####*#«##*#*#**###*###**#**###*#****              \r\n","business_name":"SPORT CHEK","phone_number":"(519) 886-6336","address":"None found.","total_price":"112.99","line_items":[{"name":"886061273078 DUAL FUSION TR","price":"$99.99"}]}}